scrapy_status_mailer/__init__.py
scrapy_status_mailer/statusmailer.py
scrapy_status_mailer-0.3.dist-info/DESCRIPTION.rst
scrapy_status_mailer-0.3.dist-info/METADATA
scrapy_status_mailer-0.3.dist-info/RECORD
scrapy_status_mailer-0.3.dist-info/WHEEL
scrapy_status_mailer-0.3.dist-info/metadata.json
scrapy_status_mailer-0.3.dist-info/top_level.txt
